netunicorn/director/infrastructure/connectors/__init__.py
netunicorn/director/infrastructure/connectors/aws.py
netunicorn_connector_aws-0.0.8.dist-info/LICENSE
netunicorn_connector_aws-0.0.8.dist-info/METADATA
netunicorn_connector_aws-0.0.8.dist-info/WHEEL
netunicorn_connector_aws-0.0.8.dist-info/top_level.txt
netunicorn_connector_aws-0.0.8.dist-info/RECORD
