Metadata-Version: 2.1
Name: netunicorn-connector-aws
Version: 0.0.8
Summary: AWS connector for netunicorn
Author-email: Roman Beltiukov <rbeltiukov@ucsb.edu>
License: MIT
Keywords: netunicorn
Classifier: Programming Language :: Python :: 3
Requires-Python: >=3.10
License-File: LICENSE
Requires-Dist: netunicorn-base <0.5.0,>=0.4.0
Requires-Dist: pyyaml
Requires-Dist: boto3
